{
  "article_id": "smart-home-kit",
  "updated_at": "2026-04-25T22:00:19.851928",
  "items": [
    {
      "name": "【楽天1位獲得】 SwitchBot ハブ2 Hub 温湿度計付き 高性能スマートリモコン IoT 家電を遠隔操作 # W3202106 スイッチボット (スマート家電・リモコン) 学習リモコン遠隔操作 エアコン アレクサ Alexa 音声操作 温度 湿度 W3202100",
      "price": 7880,
      "url": "https://hb.afl.rakuten.co.jp/hgc/g00rwh8n.1a2pr5e3.g00rwh8n.1a2psc14/?pc=https%3A%2F%2Fitem.rakuten.co.jp%2Fkitcut-ps%2F517037%2F&m=http%3A%2F%2Fm.rakuten.co.jp%2Fkitcut-ps%2Fi%2F10130570%2F&rafcid=wsc_i_is_c682bfd9-5e25-4ec2-9f1c-e7a5057cf06f",
      "affiliateUrl": "https://hb.afl.rakuten.co.jp/hgc/g00rwh8n.1a2pr5e3.g00rwh8n.1a2psc14/?pc=https%3A%2F%2Fitem.rakuten.co.jp%2Fkitcut-ps%2F517037%2F&m=http%3A%2F%2Fm.rakuten.co.jp%2Fkitcut-ps%2Fi%2F10130570%2F&rafcid=wsc_i_is_c682bfd9-5e25-4ec2-9f1c-e7a5057cf06f",
      "image": "https://thumbnail.image.rakuten.co.jp/@0_mall/kitcut-ps/cabinet/item/159/p-270375.jpg",
      "reviewCount": 98,
      "reviewAverage": 4.38,
      "quality_score": 5.23848,
      "offer_score": 5.23848,
      "shopName": "Premium Selection 楽天市場店",
      "caption": "●合わせて買いたい商品●気になる商品■ 1台で自宅をトータルコントロール 今ある家電を手軽にスマート化SwitchBot ハブ2は、IRリモコン、ハブ機能、温湿度計、スマートボタンが一つになった高性能な4-in-1スマートリモコンです。■ 究極の赤外線リモコン4800社以上83000以上の型番に対応半年周期で赤外線コードアップデートを実施。側面に補助用赤外線LEDを設置することで、送信範囲がハブミニの2倍■ 画面を最大限に活用温湿度を一目で確認して室内環境を把握ON/OFFボタンには好きなシーンを登録してワンタッチで簡単操作アラート機能で光と音を使ってお知らせ■ 革新的な技術業界初のIR De",
      "is_major": false
    }
  ]
}